UnitMatchPy/GUI.py
UnitMatchPy/GUI_icon.png
UnitMatchPy/UM Logo.ico
UnitMatchPy/__init__.py
UnitMatchPy/assign_unique_id.py
UnitMatchPy/bayes_functions.py
UnitMatchPy/default_params.py
UnitMatchPy/extract_raw_data.py
UnitMatchPy/metric_functions.py
UnitMatchPy/overlord.py
UnitMatchPy/param_functions.py
UnitMatchPy/run.py
UnitMatchPy/save_utils.py
UnitMatchPy/utils.py
UnitMatchPy/TkinterTheme/awthemes-10.4.0/LICENSE
UnitMatchPy/TkinterTheme/awthemes-10.4.0/README.txt
UnitMatchPy/TkinterTheme/awthemes-10.4.0/awdark.tcl
UnitMatchPy/TkinterTheme/awthemes-10.4.0/awlight.tcl
UnitMatchPy/TkinterTheme/awthemes-10.4.0/awtemplate.tcl
UnitMatchPy/TkinterTheme/awthemes-10.4.0/awthemes.n7
UnitMatchPy/TkinterTheme/awthemes-10.4.0/awthemes.tcl
UnitMatchPy/TkinterTheme/awthemes-10.4.0/awwinxpblue.tcl
UnitMatchPy/TkinterTheme/awthemes-10.4.0/colorutils.tcl
UnitMatchPy/TkinterTheme/awthemes-10.4.0/demoscaled.tcl
UnitMatchPy/TkinterTheme/awthemes-10.4.0/demoscaledb.tcl
UnitMatchPy/TkinterTheme/awthemes-10.4.0/demottk.tcl
UnitMatchPy/TkinterTheme/awthemes-10.4.0/pkgIndex.tcl
UnitMatchPy/TkinterTheme/awthemes-10.4.0/i/awthemes/README.txt
UnitMatchPy/TkinterTheme/awthemes-10.4.0/i/awthemes/arrow/chevron/arrow-down-d.svg
UnitMatchPy/TkinterTheme/awthemes-10.4.0/i/awthemes/arrow/chevron/arrow-down-n-base.svg
UnitMatchPy/TkinterTheme/awthemes-10.4.0/i/awthemes/arrow/chevron/arrow-down-n.svg
UnitMatchPy/TkinterTheme/awthemes-10.4.0/i/awthemes/arrow/chevron/arrow-down-sn.svg
UnitMatchPy/TkinterTheme/awthemes-10.4.0/i/awthemes/arrow/chevron/arrow-left-n.svg
UnitMatchPy/TkinterTheme/awthemes-10.4.0/i/awthemes/arrow/chevron/arrow-right-n.svg
UnitMatchPy/TkinterTheme/awthemes-10.4.0/i/awthemes/arrow/chevron/arrow-right-sn.svg
UnitMatchPy/TkinterTheme/awthemes-10.4.0/i/awthemes/arrow/chevron/arrow-up-d.svg
UnitMatchPy/TkinterTheme/awthemes-10.4.0/i/awthemes/arrow/chevron/arrow-up-n.svg
UnitMatchPy/TkinterTheme/awthemes-10.4.0/i/awthemes/arrow/open/arrow-down-n-base.svg
unitmatchpy-3.2.9.dist-info/licenses/LICENSE
unitmatchpy-3.2.9.dist-info/METADATA
unitmatchpy-3.2.9.dist-info/WHEEL
unitmatchpy-3.2.9.dist-info/top_level.txt
unitmatchpy-3.2.9.dist-info/RECORD
