Metadata-Version: 2.4
Name: UnitMatchPy
Version: 3.2.9
Summary: Automatic matching of neurons across sessions
Author: Enny van Beest, Célian Bimbard, Suyash Agarwal, Wentao Qiu
License: CC BY-NC-SA 4.0 International
Classifier: Programming Language :: Python :: 3
Classifier: Programming Language :: Python :: 3.9
Classifier: Programming Language :: Python :: 3.10
Classifier: Programming Language :: Python :: 3.11
Classifier: Programming Language :: Python :: 3.12
Classifier: Operating System :: OS Independent
Requires-Python: >=3.9
License-File: LICENSE
Requires-Dist: numpy<2.0,>=1.21
Requires-Dist: scipy<2.0,>=1.9
Requires-Dist: pandas<3.0,>=1.5
Requires-Dist: matplotlib<4.0,>=3.6
Requires-Dist: joblib<2.0,>=1.2
Requires-Dist: tqdm<5.0,>=4.64
Requires-Dist: h5py<4.0,>=3.8
Requires-Dist: scikit-learn<2.0,>=1.2
Requires-Dist: mtscomp
Requires-Dist: torch<3.0,>=2.1
Provides-Extra: full
Requires-Dist: mat73<1.0,>=0.62; extra == "full"
Requires-Dist: spikeinterface<0.120,>=0.100; extra == "full"
Provides-Extra: notebooks
Requires-Dist: ipykernel<7,>=6; extra == "notebooks"
Provides-Extra: dev
Requires-Dist: pytest; extra == "dev"
Requires-Dist: ruff; extra == "dev"
Requires-Dist: mypy; extra == "dev"
Requires-Dist: build; extra == "dev"
Requires-Dist: twine; extra == "dev"
Dynamic: license-file
